redcli/__init__.py
redcli/main.py
redcli/application/__init__.py
redcli/application/app.py
redcli/application/constant.py
redcli/application/services/__init__.py
redcli/application/services/base.py
redcli/application/services/config.py
redcli/application/services/logger.py
redcli/application/services/redis.py
redcli/application/services/resource.py
redcli/domain/__init__.py
redcli/domain/adapters/__init__.py
redcli/domain/adapters/redis.py
redcli/domain/entity/__init__.py
redcli/domain/entity/operations.py
redcli/domain/entity/redis.py
redcli/domain/services/__init__.py
redcli/domain/services/redis.py
redcli/infrastructuration/__init__.py
redcli/infrastructuration/input_components/__init__.py
redcli/infrastructuration/input_components/input_once.py
redcli/infrastructuration/input_components/input_session.py
redcli/infrastructuration/print_components/__init__.py
redcli/infrastructuration/print_components/base.py
redcli/infrastructuration/print_components/constant.py
redcli/infrastructuration/print_components/formatted_ansi_text.py
redcli/infrastructuration/print_components/formatted_html_text.py
redcli/infrastructuration/print_components/formatted_style_text.py
redcli/infrastructuration/print_components/formatted_token_text.py
redcli/infrastructuration/print_components/plain_text.py
redcli/prompt_addons/__init__.py
redcli/prompt_addons/completer.py
redcli/prompt_addons/suggestion.py
redcli/resources/config.ini
test/__init__.py
test/infrastructuration/__init__.py
test/infrastructuration/input_components/__init__.py
test/infrastructuration/print_components/__init__.py
test/infrastructuration/print_components/formatted_text.py
redcli-1.4.0.dist-info/METADATA
redcli-1.4.0.dist-info/WHEEL
redcli-1.4.0.dist-info/entry_points.txt
redcli-1.4.0.dist-info/top_level.txt
redcli-1.4.0.dist-info/RECORD
