Metadata-Version: 2.1
Name: redcli
Version: 1.4.0
Summary: Simple Redis Client Tool
Home-page: UNKNOWN
Author: zhouhao
Author-email: zhouhao19931002@hotmail.com
Maintainer: zhouhao
License: UNKNOWN
Platform: UNKNOWN
Classifier: Programming Language :: Python :: 3.7
Requires-Python: >=3.7.1
Requires-Dist: Pygments (==2.5.1)
Requires-Dist: prompt-toolkit (==3.0.1)
Requires-Dist: click (==7.0)
Requires-Dist: redis (==3.3.1)
